Metadata-Version: 2.1
Name: harmonicbalance
Version: 0.2.0
Summary: Minimalistic framework for calculating nonlinear periodic steady state responses using an object based harmonic balance.
Home-page: https://github.com/milanofthe/harmonicbalance
Author: Milan Rother
Author-email: milan.rother@gmx.de
Classifier: Programming Language :: Python :: 3
Classifier: License :: OSI Approved :: MIT License
Classifier: Operating System :: OS Independent
Requires-Python: >=3.6
License-File: LICENSE.txt
Requires-Dist: numpy
Requires-Dist: scipy
